[{"name":"Emily Ye","bias":"Hobi","message":"IM YOUR HOPPEE YOU'RE MY HOPEE I'M JHOPEE"},{"name":"Emily Ye","bias":"Hobi","message":"IM YOUR HOPPEE YOU'RE MY HOPEE I'M JHOPEE"},{"name":"Em","bias":"hobi","message":"I'M YOUR HOPEEE"},{"name":"Jess","bias":"hobi","message":"YOU'RE MY HOPEEE"},{"name":"Roger","bias":"hobi","message":"I'M JHOPEEE"},{"name":"Mel","bias":"Yoongi","message":"Yoongi meow meow"},{"name":"Ellie","message":"lachimolala"},{"name":"Jin","bias":"Jin","message":"hello yes I am world wide handsome jin"}]
